easyrag_tools/__init__.py
easyrag_tools/tools/__init__.py
easyrag_tools/tools/hello_world_tool.py
easyrag_tools/tools/tree_summerize_tool.py
easyrag_tools/tools/utils.py
easyrag_tools/tools/vector_store_tool.py
easyrag_tools/yamls/hello_world_tool.yaml
easyrag_tools/yamls/tree_summerize_tool.yaml
easyrag_tools/yamls/vector_store_tool.yaml
tests/__init__.py
tests/test_hello_world_tool.py
easyrag_tools-0.0.2.dist-info/METADATA
easyrag_tools-0.0.2.dist-info/WHEEL
easyrag_tools-0.0.2.dist-info/entry_points.txt
easyrag_tools-0.0.2.dist-info/top_level.txt
easyrag_tools-0.0.2.dist-info/RECORD
