Metadata-Version: 2.1
Name: easyrag-tools
Version: 0.0.2
Summary: This is my tools package
Requires-Dist: llama-index-llms-openai-like ==0.1.3
Requires-Dist: llama-index.embeddings.dashscope ==0.1.3
Requires-Dist: llama-index ==0.10.29
Requires-Dist: llama-index-vector-stores-analyticdb ==0.1.1
